pyrmanent/__init__.py
pyrmanent/pyrmanent_class.py
tests/__init__.py
tests/test_attributes.py
tests/test_files.py
tests/test_name.py
tests/test_persistency.py
tests/test_reset.py
pyrmanent-1.1.0.dist-info/LICENSE
pyrmanent-1.1.0.dist-info/METADATA
pyrmanent-1.1.0.dist-info/WHEEL
pyrmanent-1.1.0.dist-info/top_level.txt
pyrmanent-1.1.0.dist-info/RECORD
