Metadata-Version: 2.1
Name: pyrmanent
Version: 1.1.0
Summary: Make all your classes permanent in a flash
Home-page: https://github.com/sergioteula/pyrmanent
Author: Sergio Abad
Author-email: sergio.abad@bytelix.com
License: MIT
Keywords: python,persistence,class,permanent
Platform: UNKNOWN
Classifier: Programming Language :: Python
Classifier: Development Status :: 5 - Production/Stable
Classifier: License :: OSI Approved :: MIT License
Classifier: Operating System :: OS Independent
Classifier: Topic :: Utilities
Requires-Python: >=3.0
License-File: LICENSE
